{
  "Name": "Default SMM Catalog",
  "Assets": [
    {
      "ID": "rodriadaoaktownzip.zip",
      "IDWithoutExtension": "rodriadaoaktownzip",
      "Name": "Oak Town Park (W.I.P)",
      "Description": "WORKS WITH LATEST SESSION UPDATE!!! Currently a work in progress. No textures and some collisions are messed up and most are not perfect.",
      "Version": 1.5,
      "Author": "rodriada000",
      "DownloadLink": "rsmm://Url/https$github.com/rodriada000/SessionCustomMapReleases/releases/download/oakTown/OakTown_Park_0005_compat.zip",
      "PreviewImage": "https://github.com/rodriada000/SessionCustomMapReleases/raw/master/preview_images/oaktown_preview.png?raw=true",
      "Category": "session-maps",
      "UpdatedDate": "2020-04-27T00:00:00-07:00"
    },
    {
      "ID": "Merak.zip",
      "IDWithoutExtension": "Merak",
      "Name": "Merak",
      "Description": "Come skate surrounded by the wilderness of Merak!\n\nMap Controls:\n\nTime: Left/Right Keys\nLights: Spacebar\n\nArt Contributions:\n@Suco\n@enoksi",
      "Version": 2,
      "Author": "kylerigelhof",
      "DownloadLink": "rsmm://Url/https$github.com/rodriada000/SessionCustomMapReleases/releases/download/Merak/Merak.zip",
      "PreviewImage": "https://media.discordapp.net/attachments/626377225410707467/717006341259919370/Merak.png?width=1026&height=577",
      "Category": "session-maps",
      "UpdatedDate": "2020-06-1T00:00:00-07:00"
    },
    {
      "ID": "SkateAgora.zip",
      "IDWithoutExtension": "SkateAgora",
      "Name": "Skate Agora",
      "Description": "A model of Skate Agora in Barcelona.\n\nMap Controls:\n\nTime: Left/Right Keys\nLights: Spacebar\n\nThanks to Rafael Álvarez for being at the actual park and sending references along the way.\n\nArt Contributions:\n\n@Suco\n@Abaddon\n@enoksi",
      "Version": 2,
      "Author": "kylerigelhof",
      "DownloadLink": "rsmm://Url/https$github.com/rodriada000/SessionCustomMapReleases/releases/download/SkateAgora/Skate.Agora.zip",
      "PreviewImage": "https://media.discordapp.net/attachments/709472954236534875/720774752268058714/Skate_Agora.png?width=1026&height=577",
      "Category": "session-maps",
      "UpdatedDate": "2020-06-11T00:00:00-07:00"
    },
    {
      "ID": "ParkyB.zip",
      "IDWithoutExtension": "ParkyB",
      "Name": "Parky B",
      "Description": "Session 0.0.0.5 Compatible - Updated Parky_B. a lot of new stuff and no longer requires shadows to be turned off in-game.",
      "Version": 2.0,
      "Author": "Bers Lers",
      "DownloadLink": "rsmm://GDrive/146s-Ewqs9D-8VNtwtmHfi6YLdP59JLeW",
      "PreviewImage": "https://media.discordapp.net/attachments/626377225410707467/707574200277401631/20200504220209_1.jpg?width=1083&height=609",
      "Category": "session-maps",
      "UpdatedDate": "2020-05-11T07:00:00Z"
    },
    {
      "ID": "TonyHawk.rar",
      "IDWithoutExtension": "TonyHawk",
      "Name": "Tony Hawk",
      "Description": "Tony Hawk is in Session. This is a Tony Hawk model I tried to recreate from the upcoming THPS 1+2 game. Complete with the same board, shoes, shirt etc.  ENJOY! Thanks to Redgouf for letting my use his shorts mesh. \r\n\r\nGo into apartment and change clothes and board if need be",
      "Version": 1.0,
      "Author": "ndaoud360",
      "DownloadLink": "rsmm://MegaFile/CYY1CQBb#-RYXJyMQTpYHrkSndI9GPT2CDuAq51Q2ckXAH8Lijtg",
      "PreviewImage": "https://media.discordapp.net/attachments/614405628512698378/712047825873272852/Tony.png?width=1026&height=577",
      "Category": "session-characters",
      "UpdatedDate": "2020-05-23T07:00:00Z"
    },
    {
      "ID": "Familia.zip",
      "IDWithoutExtension": "Familia",
      "Name": "Familia HQ",
      "Description": "Familia HQ | Minneapolis, MN.\r\n\r\nAccurate replica. Look it up if you aren't familiar! ENJOY!\r\n\r\nI will be making small adjustments here and there, feel free to point out any bugs.",
      "Version": 1.0,
      "Author": "skateboarddaily",
      "DownloadLink": "rsmm://GDrive/1Z2lSlaJ_mjHOZAvrjFqAwqBqRWKQhEzr",
      "PreviewImage": "http://i3.ytimg.com/vi/8wMeZm9NDMk/maxresdefault.jpg",
      "Category": "session-maps",
      "UpdatedDate": "2020-05-26T07:00:00Z"
    }
  ]
}
